unv_scispacy_abbr/__init__.py
unv_scispacy_abbr/abbreviation.py
unv_scispacy_abbr-0.1.1.dist-info/licenses/LICENSE
unv_scispacy_abbr-0.1.1.dist-info/METADATA
unv_scispacy_abbr-0.1.1.dist-info/WHEEL
unv_scispacy_abbr-0.1.1.dist-info/top_level.txt
unv_scispacy_abbr-0.1.1.dist-info/RECORD
