Metadata-Version: 2.4
Name: unv_scispacy_abbr
Version: 0.1.1
Summary: Standalone abbreviation detection component extracted from scispacy.
Author-email: Ashok Hariharan <ashok@hariharan.org.in>
License: APACHE
Classifier: Programming Language :: Python :: 3
Classifier: Programming Language :: Python :: 3 :: Only
Classifier: License :: OSI Approved :: Apache Software License
Classifier: Operating System :: OS Independent
Requires-Python: >=3.8
License-File: LICENSE
Requires-Dist: spacy<4.0,>=3.3
Provides-Extra: test
Requires-Dist: pytest; extra == "test"
Requires-Dist: pytest-cov; extra == "test"
Requires-Dist: pytest-xdist; extra == "test"
Dynamic: license-file
